texttoolkitx/__init__.py
texttoolkitx/core.py
texttoolkitx-0.1.2.dist-info/licenses/LICENSE
texttoolkitx-0.1.2.dist-info/METADATA
texttoolkitx-0.1.2.dist-info/WHEEL
texttoolkitx-0.1.2.dist-info/top_level.txt
texttoolkitx-0.1.2.dist-info/RECORD
