Metadata-Version: 2.4
Name: texttoolkitx
Version: 0.1.2
Summary: A Python utility package for string manipulation (slugify, truncate, palindrome, etc.)
Author-email: Muhammad Mehdi <syedmuhammadmehdi159@gmail.com>
License: MIT
Requires-Python: >=3.6
License-File: LICENSE
Dynamic: license-file
